synapsense/__init__.py
synapsense/__main__.py
synapsense/context_manager.py
synapsense/context_optimizer.py
synapsense/prompt_builder.py
synapsense-1.0.3.dist-info/LICENSE
synapsense-1.0.3.dist-info/METADATA
synapsense-1.0.3.dist-info/WHEEL
synapsense-1.0.3.dist-info/top_level.txt
synapsense-1.0.3.dist-info/RECORD
