Metadata-Version: 2.1
Name: synapsense
Version: 1.0.3
Summary: SynapSense (Python In-Context Learning) is a Python library designed to facilitate the implementation of In-Context Learning (ICL) with Large Language Models (LLMs).
Home-page: https://github.com/richardsonlima/synapsense.git
Author: Richardson Lima
Author-email: contato@richardsonlima.com.br
License: BSD License
Classifier: Development Status :: 5 - Production/Stable
Classifier: Intended Audience :: Developers
Classifier: License :: OSI Approved :: BSD License
Classifier: Programming Language :: Python :: 3
Classifier: Topic :: Scientific/Engineering :: Artificial Intelligence
Classifier: Topic :: Software Development :: Libraries :: Python Modules
Requires-Python: >=3.8
License-File: LICENSE
Requires-Dist: openai >=1.46.0
Requires-Dist: nltk
Requires-Dist: stopwords
